[{"reb": 1.58, "uc_oreb": 0.22, "g": 67, "c_oreb": 0.37, "c_dreb": 0.16, "c_reb_pct": 0.34, "oreb": 0.6, "player_name_last_first": "Westbrook, Russell", "uc_reb": 1.04, "player_id": 201566, "shot_dist_range": "0-6 Feet", "sort_order": 1, "uc_dreb": 0.82, "c_reb": 0.54, "reb_frequency": 0.217, "dreb": 0.99, "uc_reb_pct": 0.66}, {"reb": 0.99, "uc_oreb": 0.1, "g": 67, "c_oreb": 0.15, "c_dreb": 0.16, "c_reb_pct": 0.318, "oreb": 0.25, "player_name_last_first": "Westbrook, Russell", "uc_reb": 0.67, "player_id": 201566, "shot_dist_range": "7-13 Feet", "sort_order": 2, "uc_dreb": 0.57, "c_reb": 0.31, "reb_frequency": 0.135, "dreb": 0.73, "uc_reb_pct": 0.682}, {"reb": 1.49, "uc_oreb": 0.18, "g": 67, "c_oreb": 0.13, "c_dreb": 0.22, "c_reb_pct": 0.24, "oreb": 0.31, "player_name_last_first": "Westbrook, Russell", "uc_reb": 1.13, "player_id": 201566, "shot_dist_range": "13-19 Feet", "sort_order": 3, "uc_dreb": 0.96, "c_reb": 0.36, "reb_frequency": 0.205, "dreb": 1.18, "uc_reb_pct": 0.76}, {"reb": 3.25, "uc_oreb": 0.39, "g": 67, "c_oreb": 0.31, "c_dreb": 0.39, "c_reb_pct": 0.216, "oreb": 0.7, "player_name_last_first": "Westbrook, Russell", "uc_reb": 2.55, "player_id": 201566, "shot_dist_range": "19+ Feet", "sort_order": 4, "uc_dreb": 2.16, "c_reb": 0.7, "reb_frequency": 0.447, "dreb": 2.55, "uc_reb_pct": 0.784}]